slovene_denormalizator/__init__.py
slovene_denormalizator/classifier.py
slovene_denormalizator/configs.py
slovene_denormalizator/construction.py
slovene_denormalizator/denormalizer.py
slovene_denormalizator/denormalizer_helpers.py
slovene_denormalizator/sentence.py
slovene_denormalizator/version.py
slovene_denormalizator/word.py
slovene_denormalizator/word_tokenizer.py
slovene_denormalizator/data/alnum_dict.pickle
slovene_denormalizator/data/denormalizator-nr100+.pickle
slovene_denormalizator/data/denormalizator-nr100.pickle
slovene_denormalizator/data/denormalizator-nr100_skl.pickle
slovene_denormalizator/data/denormalizator-nrskupaj.pickle
slovene_denormalizator/data/denormalizator-nrvelike_skl.pickle
slovene_denormalizator/data/denormalizator-nrvrst.pickle
slovene_denormalizator/data/lastnaimena.pickle
slovene_denormalizator-0.0.1.dist-info/LICENSE.md
slovene_denormalizator-0.0.1.dist-info/METADATA
slovene_denormalizator-0.0.1.dist-info/WHEEL
slovene_denormalizator-0.0.1.dist-info/top_level.txt
slovene_denormalizator-0.0.1.dist-info/RECORD
