Metadata-Version: 2.1
Name: slovene-denormalizator
Version: 0.0.1
Summary: slovene denormalizator
Home-page: UNKNOWN
Author: Peter Pisljar
License: UNKNOWN
Platform: UNKNOWN
Requires-Python: >=3.8.0, <3.12
License-File: LICENSE.md
Requires-Dist: flask
Requires-Dist: flask-restx
Requires-Dist: nltk
